mcp_python/__init__.py
mcp_python/__main__.py
mcp_python/server.py
mseep_mcp_python-0.2.2.dist-info/METADATA
mseep_mcp_python-0.2.2.dist-info/WHEEL
mseep_mcp_python-0.2.2.dist-info/entry_points.txt
mseep_mcp_python-0.2.2.dist-info/licenses/LICENSE
mseep_mcp_python-0.2.2.dist-info/RECORD
