Metadata-Version: 2.4
Name: mseep-mcp-python
Version: 0.2.2
Summary: MCP server providing a Python REPL with persistent session
Author-email: mseep <support@skydeck.ai>
Maintainer-email: mseep <support@skydeck.ai>
License-Expression: MIT
License-File: LICENSE
Keywords: mcp,python,repl,server
Classifier: Development Status :: 4 - Beta
Classifier: License :: OSI Approved :: MIT License
Classifier: Operating System :: OS Independent
Classifier: Programming Language :: Python :: 3
Classifier: Programming Language :: Python :: 3.10
Classifier: Programming Language :: Python :: 3.11
Classifier: Programming Language :: Python :: 3.12
Requires-Python: >=3.10
Requires-Dist: fastmcp>=2.2.0
Requires-Dist: llm-credential-manager
Requires-Dist: llm-parser-filter
Requires-Dist: mcp-gsuite
Requires-Dist: pytest>=8.3.5
Requires-Dist: python-dotenv
